{
      "title": "INTEL",
      "description": "",
      "hits": 0,
      "columns": [
        "intel.seen_indicator",
        "intel.seen_indicator_type",
        "intel.seen_where"
      ],
      "sort": [
        "@timestamp",
        "desc"
      ],
      "version": 1,
      "kibanaSavedObjectMeta": {
        "searchSourceJSON": "{\"index\":\"bro-*\",\"query\":{\"query_string\":{\"analyze_wildcard\":true,\"query\":\"*\"}},\"filter\":[{\"$state\":{\"store\":\"appState\"},\"meta\":{\"alias\":null,\"disabled\":false,\"index\":\"bro-*\",\"key\":\"@meta.stream\",\"negate\":false,\"value\":\"intel\"},\"query\":{\"match\":{\"@meta.stream\":{\"query\":\"intel\",\"type\":\"phrase\"}}}}],\"highlight\":{\"pre_tags\":[\"@kibana-highlighted-field@\"],\"post_tags\":[\"@/kibana-highlighted-field@\"],\"fields\":{\"*\":{}},\"require_field_match\":false,\"fragment_size\":2147483647}}"
      }
}
